[{"name":"中国传统文化","path":"api/tags/中国传统文化.json","slug":"中国传统文化","count":1},{"name":"昆曲","path":"api/tags/昆曲.json","slug":"昆曲","count":1},{"name":"云计算","path":"api/tags/云计算.json","slug":"云计算","count":1},{"name":"数据结构","path":"api/tags/数据结构.json","slug":"数据结构","count":1},{"name":"Java","path":"api/tags/Java.json","slug":"Java","count":1},{"name":"虚拟机","path":"api/tags/虚拟机.json","slug":"虚拟机","count":1},{"name":"算法","path":"api/tags/算法.json","slug":"算法","count":3},{"name":"计算机体系结构","path":"api/tags/计算机体系结构.json","slug":"计算机体系结构","count":1},{"name":"课程笔记","path":"api/tags/课程笔记.json","slug":"课程笔记","count":2}]